Bank_of_Tz/Bank_of_Tz.py
Bank_of_Tz/__init__.py
Bank_of_Tz-0.2.dist-info/METADATA
Bank_of_Tz-0.2.dist-info/RECORD
Bank_of_Tz-0.2.dist-info/WHEEL
Bank_of_Tz-0.2.dist-info/top_level.txt
