Metadata-Version: 2.1
Name: Bank-of-Tz
Version: 0.2
Summary: Gets data from  the Bank of Tanzania
Home-page: https://github.com/Mbonea-Mjema/Bank-of-Tanzania-Tbill-Tbond-
Author: Mbonea Mjema
Author-email: mjema86@gmail.com
License: MIT
Keywords: Bonds
Platform: UNKNOWN
Classifier: Development Status :: 3 - Alpha
Classifier: License :: OSI Approved :: MIT License
Classifier: Programming Language :: Python :: 3
Classifier: Topic :: Utilities
Requires-Dist: bs4
Requires-Dist: requests
